controlCircuit.v
`include "defines.h"

module controlCircuit(
	// INPUTS
	input wire [15:0] instr,
	input wire clk,
	// OUTPUTS
	output reg ext_data_en,
	output reg ext_data_low_reg_en,
	output reg [7:0] reg_in_en,
	output reg [7:0] reg_out_en,
	output reg alu_reg_en,
	output reg alu_sel,
	output reg alu_out_en,
	output reg g_reg_en,
	output reg done
	);

	reg [3:0] opcode, RX, RY;

	reg [4:0] state, next_state;
	reg [7:0] enable_8bit;

	initial begin
		state <= `STATE_RESET;
	end

	always @(negedge clk) begin 
		opcode = instr[15:12];
		RX = instr[11:8];
		RY = instr[7:4];
	    
	    case(opcode)
	        `INSTR_NOP : next_state = `STATE_RESET;
	        `INSTR_LOAD : begin 
	            case (state) 
	                `STATE_RESET : next_state = `STATE_LOAD1;
	                `STATE_LOAD1 : next_state = `STATE_LOAD2;
	                `STATE_LOAD2 : next_state = `STATE_RESET;
	                default : next_state = `STATE_RESET;
	            endcase
	        end
	        `INSTR_MOV : begin
	        	case (state)
	        		`STATE_RESET : next_state = `STATE_MOV;
	        		`STATE_MOV : next_state = `STATE_RESET;
	        		default: next_state = `STATE_RESET;
	        	endcase
			end
            `INSTR_ADD : begin
            	case (state)
            		`STATE_RESET : next_state = `STATE_ALU;
            		`STATE_ALU: next_state = `STATE_ADD;
            		`STATE_ADD : next_state = `STATE_G;
            		`STATE_G : next_state = `STATE_RESET;
            		default: next_state = `STATE_RESET;
            	endcase
            end
			`INSTR_XOR : begin
            	case (state)
            		`STATE_RESET : next_state = `STATE_ALU;
            		`STATE_ALU: next_state = `STATE_XOR;
            		`STATE_XOR : next_state = `STATE_G;
            		`STATE_G : next_state = `STATE_RESET;
            		default: next_state = `STATE_RESET;
            	endcase
            end
            default : next_state = `STATE_RESET;
	    endcase
	   	state <= next_state;
	end

	always @(state) begin // CORRECT
		case (state)
			`STATE_RESET : begin
				ext_data_en = 1'b0;
				ext_data_low_reg_en = 1'b0;
				reg_in_en = 8'b00000000;
				reg_out_en = 8'b00000000;
				alu_reg_en = 1'b0;
				alu_sel = 1'b0;
				alu_out_en = 1'b0;
				g_reg_en = 1'b0;
				done = 1'b1;
			end
			`STATE_LOAD1 : begin
				ext_data_low_reg_en = 1'b1;
				done = 1'b0;
			end
			`STATE_LOAD2 : begin
				ext_data_low_reg_en = 1'b0;
				ext_data_en = 1'b1;
				reg_in_en[RX] = 1'b1;
				done = 1'b0;
			end
			`STATE_MOV : begin
				reg_in_en[RX] = 1'b1;
				reg_out_en[RY] = 1'b1;
				done = 1'b0;
			end
			`STATE_ALU : begin
				reg_out_en[RX] = 1'b1;
				alu_reg_en = 1'b1;
				done = 1'b0;
			end
			`STATE_ADD : begin
				reg_out_en[RX] = 1'b0;
				reg_out_en[RY] = 1'b1;
				alu_reg_en = 1'b0;
				alu_sel = 1'b0;
				g_reg_en = 1'b1;
				done = 1'b0;
			end
			`STATE_XOR : begin
				reg_out_en[RX] = 1'b0;
				reg_out_en[RY] = 1'b1;
				alu_reg_en = 1'b0;
				alu_sel = 1'b1;
				g_reg_en = 1'b1;
				done = 1'b0;
			end
			`STATE_G : begin
				reg_out_en[RY] = 1'b0;
				g_reg_en = 1'b0;
				alu_out_en = 1'b1;
				reg_in_en[RX] = 1'b1;
				done = 1'b0;
			end
            default : begin
                // To handle any undefined states, assign default values again
                ext_data_en = 1'b0;
                reg_in_en = 8'b00000000;
                reg_out_en = 8'b00000000;
                alu_reg_en = 1'b0;
                alu_sel = 1'b0;
                alu_out_en = 1'b0;
                g_reg_en = 1'b0;
                done = 1'b1;
            end			
		endcase
	end


endmodule

CC_TB.v
module CC_TB;

    reg clk;
    reg [3:0] count; 
    reg [15:0] instr;  
    wire ext_data_en;
    wire ext_data_low_reg_en;
    wire [7:0] reg_in_en;
    wire [7:0] reg_out_en;
    wire alu_reg_en;
    wire alu_sel;
    wire alu_out_en;
    wire g_reg_en;
    wire done;

    controlCircuit pleasework(
        .instr(instr),
        .clk(clk),
        .ext_data_en(ext_data_en),
        .ext_data_low_reg_en(ext_data_low_reg_en),
        .reg_in_en(reg_in_en),
        .reg_out_en(reg_out_en),
        .alu_reg_en(alu_reg_en),
        .alu_sel(alu_sel),
        .alu_out_en(alu_out_en),
        .g_reg_en(g_reg_en),
        .done(done)
    );

    initial begin 
        count = 4'b0000;
        clk = 1'b0;
    end
    
    always begin
        #50 clk = ~clk; // Toggle clock every 50 time units
    end
    
    always @(posedge clk) begin
        count = count + 4'b0001;
    end
    
    always @(count) begin
        case (count)
            // load 16'b0000000000000001 into R1
            4'b0000 : instr = 16'b0000000100000000; 
            4'b0001 : instr = 16'b0000000100000001;
            4'b0010 : instr = 16'b0000000100000001;

            // load 16'b0000000000000001 into R2
            4'b0011 : instr = 16'b0000001000000001; 
            4'b0100 : instr = 16'b0000001000000001; 
            4'b0101 : instr = 16'b0000001000000001; 
            4'b0110 : instr = 16'b0000000000000000; 
            4'b0111 : instr = 16'b0000000000000000; 
            4'b1000 : instr = 16'b0000000000000000; 
            4'b1001 : instr = 16'b0000000000000000; 
            4'b1010 : instr = 16'b0000000000000000; 
            4'b1011 : instr = 16'b0000000000000000; 
            4'b1100 : instr = 16'b0000000000000000; 
            4'b1101 : instr = 16'b0000000000000000; 
            4'b1110 : instr = 16'b0000000000000000; 
            4'b1111 : instr = 16'b0000000000000000; 
            default : instr = 16'b0000000000000000; 
        endcase
    end

    initial begin
        $dumpfile("CC_TB.vcd");
        $dumpvars(0, CC_TB);
        #2000 $finish;
    end

endmodule

CC_TB.vcd
$date
	Mon May 20 19:43:40 2024
$end
$version
	Icarus Verilog
$end
$timescale
	1s
$end
$scope module CC_TB $end
$var wire 1 ! done $end
$var wire 8 " reg_out_en [7:0] $end
$var wire 8 # reg_in_en [7:0] $end
$var wire 1 $ g_reg_en $end
$var wire 1 % ext_data_low_reg_en $end
$var wire 1 & ext_data_en $end
$var wire 1 ' alu_sel $end
$var wire 1 ( alu_reg_en $end
$var wire 1 ) alu_out_en $end
$var reg 1 * clk $end
$var reg 4 + count [3:0] $end
$var reg 16 , instr [15:0] $end
$scope module pleasework $end
$var wire 1 * clk $end
$var wire 1 ! done $end
$var wire 16 - instr [15:0] $end
$var reg 4 . RX [3:0] $end
$var reg 4 / RY [3:0] $end
$var reg 1 ) alu_out_en $end
$var reg 1 ( alu_reg_en $end
$var reg 1 ' alu_sel $end
$var reg 1 & ext_data_en $end
$var reg 1 % ext_data_low_reg_en $end
$var reg 1 $ g_reg_en $end
$var reg 5 0 next_state [4:0] $end
$var reg 4 1 opcode [3:0] $end
$var reg 8 2 reg_in_en [7:0] $end
$var reg 8 3 reg_out_en [7:0] $end
$var reg 5 4 state [4:0] $end
$upscope $end
$upscope $end
$enddefinitions $end
$comment Show the parameter values. $end
$dumpall
$end
#0
$dumpvars
b0 4
b0 3
b0 2
b0 1
b0 0
b0 /
b1 .
b100000000 -
b100000000 ,
b0 +
0*
0)
0(
0'
0&
x%
0$
b0 #
b0 "
z!
$end
#50
b100000001 ,
b100000001 -
b1 +
1*
#100
b1 0
0*
#150
1%
b10 +
b1 4
1*
#200
b10000 0
0*
#250
b10 .
b10 #
b10 2
1&
0%
b1000000001 ,
b1000000001 -
b10000 4
b11 +
1*
#300
b0 0
0*
#350
b0 #
b0 2
0&
b100 +
b0 4
1*
#400
b1 0
0*
#450
1%
b1 4
b101 +
1*
#500
b10000 0
0*
#550
b0 .
b0 ,
b0 -
b100 #
b100 2
1&
0%
b110 +
b10000 4
1*
#600
b0 0
0*
#650
b0 #
b0 2
0&
b0 4
b111 +
1*
#700
b1 0
0*
#750
1%
b1000 +
b1 4
1*
#800
b10000 0
0*
#850
b1 #
b1 2
1&
0%
b10000 4
b1001 +
1*
#900
b0 0
0*
#950
b0 #
b0 2
0&
b1010 +
b0 4
1*
#1000
b1 0
0*
#1050
1%
b1 4
b1011 +
1*
#1100
b10000 0
0*
#1150
b1 #
b1 2
1&
0%
b1100 +
b10000 4
1*
#1200
b0 0
0*
#1250
b0 #
b0 2
0&
b0 4
b1101 +
1*
#1300
b1 0
0*
#1350
1%
b1110 +
b1 4
1*
#1400
b10000 0
0*
#1450
b1 #
b1 2
1&
0%
b10000 4
b1111 +
1*
#1500
b0 0
0*
#1550
b1 .
b100000000 ,
b100000000 -
b0 #
b0 2
0&
b0 +
b0 4
1*
#1600
b1 0
0*
#1650
1%
b100000001 ,
b100000001 -
b1 4
b1 +
1*
#1700
b10000 0
0*
#1750
b10 #
b10 2
1&
0%
b10 +
b10000 4
1*
#1800
b0 0
0*
#1850
b10 .
b0 #
b0 2
0&
b1000000001 ,
b1000000001 -
b0 4
b11 +
1*
#1900
b1 0
0*
#1950
1%
b100 +
b1 4
1*
#2000
b10000 0
0*
